{"fe_chrome_index.md":"D1c0iHy1","fe_js_class.md":"7Z5YxDtr","ee_components_index.md":"Cx9ssrQI","fe_js_grammar.md":"Bp8Ebmga","ee_dev_keil_index.md":"C1p-OKcR","rd_linux_ssh.md":"QH5uSjq5","rd_node_git.md":"qCvOLh3i","rd_linux_software.md":"BsznaW4d","rd_java_spring_index.md":"CuK8Gqeh","fe_vitepress_index.md":"Cn5OAVHQ","fe_vue_docs_01_base.md":"B9QoFGhl","rd_node_library_index.md":"BeiSTiOJ","fe_css_index.md":"3TVU4IHM","rd_java_spring_wiki_04-user.md":"DT9wlqT_","fe_vue_docs_index.md":"B1zeyIJC","fe_vue_vite_quickstart.md":"DWWy-hMc","fe_js_functions.md":"ZIu902bV","ee_db_esp8266.md":"a03E-rnw","fe_vue_vite_index.md":"CbcsXwOR","rd_node_koa_koa2-sina-05.md":"A5Vrl5zk","fe_vue_vuepress.md":"CqKdfH6z","fe_html_02_page.md":"BG166i_c","fe_web_3d_elem.md":"OEvufPIH","rd_node_nest_book-admin_01.md":"CJCZ3j6R","rd_business_web.md":"-1BdfunX","fe_react_index.md":"CGNqxrBA","rd_java_spring_liulaoshi_01_env.md":"tKDaOXjD","fe_others_eslint_index.md":"DFhqZn2l","rd_node_library_sequelize_02.md":"BUsB8eYp","rd_node_library_nodemailer_index.md":"D6JAKMOz","rd_java_spring_itheima_spring_index.md":"ZrwcV_SE","ee_db_index.md":"CK9_qXPS","fe_others_git_index.md":"D6LJfz9x","rd_node_index.md":"B8T4yPvR","fe_css_tailwind_index.md":"BjbFMiDn","rd_node_library_sequelize_01.md":"BmfDQh5R","rd_node_library_sequelize_index.md":"D4QB1fij","rd_java_index.md":"Aaeac8Nv","fe_web_3d_index.md":"ByQ6y2Vu","fe_typescript_index.md":"rglOZ3d2","rd_node_library_modbus-serial_index.md":"CN_lP_rY","fe_typescript_core_basic.md":"CdwGiDWb","rd_java_development_mybatis.md":"CJWXqUlj","ee_c_index.md":"DtV8_U61","rd_node_nest_book-admin_02.md":"Bqf4z80E","fe_vue_vben_index.md":"DvkJ67TW","rd_java_grammar_advance.md":"BZYdjnUF","rd_java_spring_wiki_01-book.md":"CB4O5sO4","rd_java_spring_deploy.md":"C_qv3DjC","ee_db_stm32f103_index.md":"Biw2O-IF","fe_others_prettier_index.md":"Q48pvFSf","ee_dev_arduino_index.md":"BKtixSbS","fe_web_3d_echarts_index.md":"D3OUK8--","fe_web_3d_echarts_02_commonconfig.md":"B5IdDW_0","fe_html_03_text.md":"BWzXo5bI","fe_css_ele_index.md":"BKNiy-pF","rd_java_spring_wiki_02-classification.md":"Ca2xpi_I","rd_java_spring_wiki_03-document.md":"Bp3T1RMo","fe_vue_vue-router.md":"DYlTyA1g","rd_node_koa_koa2-sina-01.md":"BSSJcUVu","fe_js_arrays.md":"CWk8_6bV","fe_others_electron_index.md":"HivCd_4j","rd_java_spring_liulaoshi_02_start.md":"Cd2xYHJ2","rd_java_spring_itheima_spring_01_base.md":"DNP9Fuhh","fe_web_3d_webgpu_base.md":"apRcpfz0","fe_index.md":"ClK6F4OD","rd_node_koa_koa2-sina-07.md":"Bw7U5-_G","rd_linux_software_onboard_index.md":"CDTqKmKt","rd_node_koa_index.md":"IG29xN-a","rd_node_core_config.md":"mQZTV-fI","fe_css_tailwind_01_quickstart.md":"CgBUW5BM","rd_node_core_module.md":"D3-nzkcy","rd_java_grammar_index.md":"BDY-EHhD","rd_node_core_fs.md":"Dc6mfsvr","rd_node_koa_koa2-sina-02.md":"DiEyrKfK","fe_js_regular.md":"CIhcl2DH","ee_index.md":"DhDFYCl9","fe_html_01_base.md":"CGvNU6Wf","fe_js_objects.md":"CGDkFGk7","fe_others_axios_index.md":"BmVlIxZp","rd_node_core_tcp.md":"ByaWyk08","fe_tools_vscode_index.md":"k9ZHVyJ9","rd_java_knowledge.md":"DbB5GSq3","rd_node_nest_book-admin_03.md":"Bq8vwLJz","rd_node_express_philosophy_index.md":"BVW1R8dz","rd_node_core_http.md":"CDPKou95","rd_node_nest_cli.md":"DmSOjx6p","rd_java_grammar_oo.md":"CiH8Ow6f","economy_macro_situation_japan_index.md":"CmRoQjrU","economy_stock_market_average.md":"Bfiv7E-1","economy_stock_year_2024.md":"ChKJfZiF","economy_macro_chaos.md":"D6PZR37s","economy_macro_crisis_2022_index.md":"Br_kpPie","economy_macro_analyze_bridgewater_20240409.md":"BekdBvVR","economy_stock_index.md":"Csb4wqYJ","economy_macro_situation_china_supply.md":"jLfK5anX","economy_stock_trend_theory.md":"DMG2MYKK","economy_stock_0.md":"C4zlbEvd","rd_node_nest_book-admin_index.md":"BoZN9HRr","work_logs_xintiandi_index.md":"BSKa0MbG","rd_windows_index.md":"BmcPN4ko","economy_macro_situation_china_china2024.md":"21uBiHYq","rd_node_nest_book-admin_05.md":"CfKgHZIi","economy_stock_trend_indicator.md":"B0cYSzwq","economy_macro_situation_japan_240319.md":"AEtLBkNx","iot_computer_net_index.md":"DsQwpcXe","iot_computer_net_03.md":"CIAKGX9G","iot_computer_net_04.md":"CgswgjrV","practice_zhenpath_operate.md":"DbxdtW1t","practice_zhenpath_optimize.md":"BVrQSxH-","economy_macro_data.md":"Dq1j2DT_","fe_css_elem.md":"Dtfj6bWe","iot_computer_os_index.md":"DFtbfezv","iot_interview_index.md":"DxAB3q96","iot_computer_composition_01.md":"DlWieR_u","iot_perception.md":"BINZYwj_","iot_computer_examination.md":"BfdFTbXz","iot_computer_index.md":"Cdpq-I3d","iot_computer_composition_03.md":"C7rRExnu","iot_index.md":"-9QnUPVi","iot_computer_net_01.md":"ap1mXqWl","iot_computer_os_03.md":"Di0g6lsY","iot_computer_os_02.md":"NQs3BAxb","practice_zhenpath_frontend_chaos.md":"D0iWMUFc","iot_program_char.md":"CM9ekn-q","markdown-examples.md":"BawkpXib","practice_index.md":"0OF0IClK","practice_zhenpath_backend_chaos.md":"alTJaxb4","fe_js_index.md":"11mwWDlR","practice_zhenpath_backend_database.md":"B9m7IhK1","iot_program_index.md":"uJPI1l3k","practice_bookmanage_index.md":"DBUp4ZIU","practice_zhenpath_chaos.md":"Dt3oKq8s","economy_stock_bitcion_system.md":"nC_NReNm","iot_computer_os_01.md":"Beatk1No","iot_computer_os_04.md":"CRL21J5Y","iot_computer_philosophy_index.md":"6vSiTNtS","practice_zhenpath_design.md":"BSJ7VhJ1","iot_computer_net_02.md":"DNnHg0vh","economy_stock_trend_concept.md":"Cj-dTJCK","iot_computer_composition_index.md":"BxUdSRR7","fe_vue_vue-sunday_index.md":"jhnQLsD0","iot_computer_composition_02.md":"CCKLm7nM","rd_java_idea_index.md":"CBEN_mUK","fe_vue_index.md":"D-HCmSup","fe_html_index.md":"C5wWCmua","rd_net_socket.md":"cxJ1Eco1","fe_others_ajax_index.md":"CHriOQ60","rd_node_nest_book-admin_04.md":"s005wbDf","fe_js_map.md":"COANKG4a","ee_repair_index.md":"DO6txVpb","practice_zhenpath_project_deploy.md":"CaDtyu20","fe_typescript_core_functions.md":"CXG16FV9","fe_typescript_core_class.md":"BqB7uyRM","fe_vue_core_chaos.md":"Dq_dm5Q-","practice_zhenpath_survey.md":"Bbzg6yqW","economy_stock_year_index.md":"Cj5oCp-9","practice_zhenpath_project_framework.md":"OzNMlRB4","practice_zhenpath_requirement.md":"CieQTy9z","practice_zhenpath_study.md":"CU2BjO_n","practice_zhenpath_ideas.md":"zMjJ8VPz","fe_others_index.md":"DoUw_qmT","rd_java_spring_wiki_index.md":"Bp5_ogzj","ee_components_dht11_index.md":"BhKSUPjV","fe_web_3d_webgpu_index.md":"BpCewM_o","rd_linux_index.md":"C_iS0uyB","fe_vue_nuxt_index.md":"CwXtK0Xi","practice_zhenpath_manage.md":"SJjIEIaU","index.md":"BjUrCXr8","fe_html_04_image.md":"hMzGKaW9","fe_css_antdv_index.md":"D7tU7gJf","iot_communication_data.md":"DDMUQ3r6","fe_js_set.md":"DXcxLVhU","iot_communication_index.md":"Bk-90C_i","practice_zhenpath_index.md":"BT-7nBOP","thought_world_dao.md":"CiQeBDBy","economy_macro_situation_china_index.md":"DFhyuYoz","rd_java_spring_wiki_06-libraries.md":"BeD4jgdy","economy_stock_market_index.md":"DFsIC8im","rd_java_grammar_practice.md":"uW7G_FXM","practice_zhenpath_web_index.md":"8nsWo9h7","thought_index.md":"BEPl7M9t","thought_laozi_index.md":"BWPqYXVa","fe_others_login.md":"WH1Dh72F","fe_web_3d_echarts_01_quickstart.md":"CbdRu3hU","thought_world_chaos.md":"BMMFf7es","ee_components_oled_index.md":"7lDnYoox","rd_index.md":"BOMA_P3A","economy_macro_index.md":"Da0zfdKs","fe_typescript_core_decorator.md":"EVE-3mg5","rd_tools_mysql_index.md":"n-Je_PB0","rd_java_development_index.md":"wvtTFaj3","rd_java_spring_liulaoshi_index.md":"BYDI0bCu","rd_java_spring_construction.md":"DIzgO5Ri","rd_net_index.md":"CrUH9Rpi","ee_dev_index.md":"C6oLO6Zp","rd_node_express_index.md":"RdFPIGPV","fe_vue_vue-sunday_01.md":"CSu8qS-O","rd_node_core_code.md":"DznAzcPY","rd_business_index.md":"DfOus-vE","rd_node_koa_koa2-sina-04.md":"DTr9SegQ","fe_typescript_core_everyday-type.md":"Puq-Mebu","economy_stock_bitcion_index.md":"q4pocTjw","thought_zhuangzi_02-qiwulun.md":"CShFivsa","thought_zhuangzi_01-xiaoyaoyou.md":"B3jBbNyg","economy_macro_crisis_index.md":"DW_YkthQ","thought_zhuangzi_03-yangshengzhu.md":"QHoXEOPk","thought_zhuangzi_index.md":"BWXQxJod","thought_world_index.md":"Bv83jlY7","work_deploy_dual-system.md":"D4cwLF54","thought_world_cycle.md":"BhuwQYNt","fe_vue_vben_init.md":"CS3kX6VR","economy_macro_situation_china_employment.md":"DfOd2wNK","economy_macro_dao.md":"Xr4jtZIQ","work_deploy_ubuntu_index.md":"Cj4rz7kq","work_deploy_ubuntu_03_config.md":"9WgW1bgP","work_deploy_windows_env.md":"BGi1v_re","work_devices_zh-t08r-14n1_strain-8r.md":"BMj33cfk","work_devices_tp-link_tl-ap302p.md":"BZw8_CBM","work_devices_dahua_camera.md":"CPJz93s5","work_devices_cosofteck_index.md":"Cbb5cPZr","work_devices_index.md":"CfJXFQPq","work_devices_dahua_index.md":"BZD2StKT","work_index.md":"Bq3x8Hil","work_logs_tortoisesvn.md":"DMCLUzXu","work_logs_index.md":"DCEHUaqb","work_logs_baowu_240325.md":"ByFTZ-v5","work_logs_binzhou_240402.md":"Cs_ekes4","work_logs_port.md":"BElUudWM","work_logs_jinding_index.md":"Bgz4o5C9","work_logs_ks_index.md":"C5I6LRkt","work_logs_sxt_index.md":"Bdw34m3N","work_logs_vivo_240325.md":"BiD6TiOY","work_logs_taikang_240325.md":"okZ78Wt3","economy_stock_trend_index.md":"Bd-ozEgy","rd_node_koa_koa2-sina-03.md":"BcPaSBmu","economy_book_两次全球大危机的比较研究_index.md":"C67IDE_2","economy_macro_situation_index.md":"DFSzaMWQ","rd_tools_redis.md":"VZjrSKBY","rd_node_nest_controllers.md":"BBx7szjG","economy_macro_subject_index.md":"CWo9BTLM","work_software_xiot-nest_index.md":"DbPlPgsu","rd_node_quanzhan_index.md":"CBfV7doq","rd_philosophy.md":"DOvmor5E","rd_python_index.md":"C4SSWNr-","rd_python_grammar_index.md":"CeiX4a4Z","rd_rust_index.md":"BaCuWB8A","fe_js_basictype.md":"D_xo5mm7","rd_spider_index.md":"-EeWlOC1","rd_python_pycharm_index.md":"y0iMGIHb","rd_net_tcp.md":"8I3vOYHF","rd_java_spring_wiki_05-statistics.md":"BTbhhsHt","rd_node_koa_koa2-sina-06.md":"MlCG5xeW","rd_tools_docker_index.md":"CqlANe_u","rd_tools_baota_index.md":"fKJmi3NL","work_deploy_ubuntu_02_dev.md":"UygqqO63","work_devices_oray_r300.md":"unbeyB40","work_logs_whal_index.md":"9cd8D6j-","work_software_485horizontal.md":"8PVubak4","economy_macro_situation_japan_interest.md":"exRyTyur","work_youren_lg206_index.md":"C2bvIGj3","rd_node_nest_common.md":"BO22W7vG","work_software_shmcom_index.md":"Xi1qN1Gg","work_software_modbus_strain.md":"BJZsweLU","rd_node_nest_quickstart.md":"OFVValhS","rd_node_nest_techniques.md":"MrabsRNN","rd_node_nest_index.md":"DxsDxSnn","rd_node_nest_efficient.md":"BQCmOgDs","rd_node_quanzhan_webapp-02.md":"Cc1LBFLY","work_software_data.md":"DRqDOrrl","rd_node_nest_providers.md":"CyYhJVQD","work_software_common.md":"DXmkH2t6","work_youren_index.md":"Chw_teq6","work_software_xiot_index.md":"DpDUImFF","rd_node_nest_specification.md":"CItfyloV","rd_node_test_getsubtitle_index.md":"gpC9I3JC","work_software_485.md":"DaWKoVUQ","work_software_xiot_typroot.md":"Sz6rQrXm","rd_node_quanzhan_webapp-03.md":"CbyC9d52","work_software_xiot_initserver.md":"CzT9CJHl","work_software_xiot_sysctxt.md":"mVHYlFcC","work_ysb_openstd.md":"BgNqp-PI","work_software_xiot-nest_vite-project_index.md":"DxqXBU3p","work_ysb_vibratingwire_index.md":"CkqWxQLt","work_youren_usr-tcp232-306_index.md":"BBzTvPDk","work_software_index.md":"xdObfIzP","work_software_explorer.md":"59FxX2hQ","work_ysb_level_index.md":"sarbK4yu","work_ysb_vibratingwire_03-software.md":"B191wuMr","rd_node_quanzhan_webapp-04.md":"Cs0FOtmI","rd_node_spider_index.md":"0c6oAjKb","work_software_function.md":"jUZ06VQB","work_ysb_level_level-i.md":"BemTCMNa","work_software_xiot_iotdata.md":"8q78G4lw","work_ysb_vibratingwire_02-instrument.md":"CAHKsFN4","work_devices_farsens_index.md":"NB1mFRVC","work_youren_usr-tcp232-306_485.md":"CiABDp6J","work_ysb_seismometer_index.md":"BFoZkqIQ","rd_node_quanzhan_webapp-01.md":"BSzYrppA","work_ysb_vibratingwire_01-sensor.md":"DrojpJGu","work_devices_mercury_index.md":"CAshoqmt","work_ysb_explorer_index.md":"DOwbkhoa","rd_tools_index.md":"D-XryzX0","fe_js_es6.md":"_FePJn2t","work_ysb_485inclinometer_index.md":"e4K3Jj74","work_software_xiot_cfgroot.md":"qmHEukCw","work_ysb_index.md":"BB3W2y0f","work_deploy_index.md":"PWW45MER","work_deploy_ubuntu_01_system.md":"C1E8_ym6","work_software_231104-kunshan.md":"Cu56fO4W"}
